djangocms_gist/__init__.py
djangocms_gist/admin.py
djangocms_gist/cms_plugins.py
djangocms_gist/models.py
djangocms_gist/migrations/0001_initial.py
djangocms_gist/migrations/__init__.py
djangocms_gist/templates/djangocms_gist/_gist_plugin.html
djangocms_gist-0.2.1.dist-info/DESCRIPTION.rst
djangocms_gist-0.2.1.dist-info/METADATA
djangocms_gist-0.2.1.dist-info/RECORD
djangocms_gist-0.2.1.dist-info/WHEEL
djangocms_gist-0.2.1.dist-info/metadata.json
djangocms_gist-0.2.1.dist-info/top_level.txt
